conan_unified_api/__init__.py
conan_unified_api/common.py
conan_unified_api/conan_v1.py
conan_unified_api/conan_v2.py
conan_unified_api/types.py
conan_unified_api/unified_api.py
conan_unified_api/base/__init__.py
conan_unified_api/base/helper.py
conan_unified_api/base/logger.py
conan_unified_api/base/typing.py
conan_unified_api/cache/__init__.py
conan_unified_api/cache/conan_cache.py
conan_unified_api-2.24.0.dist-info/licenses/LICENSE
conan_unified_api-2.24.0.dist-info/METADATA
conan_unified_api-2.24.0.dist-info/WHEEL
conan_unified_api-2.24.0.dist-info/top_level.txt
conan_unified_api-2.24.0.dist-info/RECORD
