Metadata-Version: 2.4
Name: conan-unified-api
Version: 2.24.0
Summary: Compatibility layer for Conan 1 and 2 for Python 3.9+
Author: Péter Gosztolya and Contributors
License: MIT License
Project-URL: repository, https://github.com/goszpeti/conan_unified_api.git
Project-URL: issues, https://github.com/goszpeti/conan_unified_api/issues
Keywords: conan,api
Classifier: Programming Language :: Python :: 3
Classifier: Programming Language :: Python :: Implementation :: CPython
Requires-Python: <3.15,>=3.9
License-File: LICENSE
Requires-Dist: conan<2.25,>=1.48
Requires-Dist: contextlib-chdir==1.0.2; python_version < "3.11"
Requires-Dist: typing-extensions<5,>=3.10.0.2
Requires-Dist: packaging
Provides-Extra: dev
Requires-Dist: rope; extra == "dev"
Provides-Extra: test
Requires-Dist: legacy-cgi; python_version >= "3.13" and extra == "test"
Requires-Dist: psutil==7.2.1; extra == "test"
Requires-Dist: pytest==8.3.5; extra == "test"
Requires-Dist: pytest-cov==5.0.0; extra == "test"
Requires-Dist: pytest-mock==3.15.1; extra == "test"
Requires-Dist: pytest-check==2.4.2; extra == "test"
Dynamic: license-file
